papayasaurus/__init__.py
papayasaurus/env.py
papayasaurus/proteins.py
papayasaurus-0.1.dist-info/METADATA
papayasaurus-0.1.dist-info/WHEEL
papayasaurus-0.1.dist-info/top_level.txt
papayasaurus-0.1.dist-info/RECORD
