Metadata-Version: 2.1
Name: papayasaurus
Version: 0.1
Summary: papayasaurus is a new light-weight library for protein simulating and modeling. It is both user friendly and easy to use!
Home-page: https://github.com/pythoncodes22/guavasaurus
Author: Idrees Ahmad
Author-email: pythoncodes22@example.com
Classifier: Programming Language :: Python :: 3
Classifier: License :: OSI Approved :: MIT License
Classifier: Operating System :: OS Independent
Requires-Python: >=3.6
